setup.py
project/main.py
ryd33n_auth_util_ver0_1.egg-info/PKG-INFO
ryd33n_auth_util_ver0_1.egg-info/SOURCES.txt
ryd33n_auth_util_ver0_1.egg-info/dependency_links.txt
ryd33n_auth_util_ver0_1.egg-info/top_level.txt