Metadata-Version: 2.1
Name: ryd33n-auth-util-ver0-1
Version: 1.0
Summary: Auth system
Home-page: https://www.python.org/sigs/distutils-sig/
Author: Dmitry "ryd33n" Kozlovsky
Author-email: rem.dk83@gmail.com
